dbeacon/__init__.py
dbeacon/beacon.py
dbeacon/scanner.py
dbeacon/utils.py
pydBeacon-1.0.0.dist-info/LICENSE
pydBeacon-1.0.0.dist-info/METADATA
pydBeacon-1.0.0.dist-info/WHEEL
pydBeacon-1.0.0.dist-info/top_level.txt
pydBeacon-1.0.0.dist-info/RECORD
