Metadata-Version: 2.1
Name: pydBeacon
Version: 1.0.0
Summary: An open source Python library for reading/writing Disney Theme Park Bluetooth Beacon data.
Home-page: https://github.com/thetestgame/pydBeacon
Author: Jordan Maxwell
Maintainer: Jordan Maxwell
License: MIT
Classifier: Programming Language :: Python :: 3
License-File: LICENSE
